uniformat/__init__.py
uniformat/cli.py
uniformat/converter.py
uniformat/detectors.py
uniformat/enums.py
uniformat/parsers/__init__.py
uniformat/parsers/toon_parser.py
uniformat-0.1.0.dist-info/licenses/LICENSE
uniformat-0.1.0.dist-info/METADATA
uniformat-0.1.0.dist-info/WHEEL
uniformat-0.1.0.dist-info/entry_points.txt
uniformat-0.1.0.dist-info/top_level.txt
uniformat-0.1.0.dist-info/RECORD
