Metadata-Version: 2.4
Name: uniformat
Version: 0.1.0
Summary: A universal data format converter for TOON, JSON, YAML, and XML
Home-page: https://github.com/sumeetkumarnaik/uniformat
Author: Sumeet Kumar Naik
Author-email: sumeet@example.com
License: MIT
Requires-Python: >=3.8
License-File: LICENSE
Requires-Dist: pyyaml
Requires-Dist: xmltodict
Dynamic: license-file
